Products.ATContentTypes-3.0.7-py2.7-nspkg.pth
Products/ATContentTypes/__init__.py
Products/ATContentTypes/atct.py
Products/ATContentTypes/browser.zcml
Products/ATContentTypes/config.py
Products/ATContentTypes/configure.zcml
Products/ATContentTypes/factories.py
Products/ATContentTypes/interface.py
Products/ATContentTypes/permission.py
Products/ATContentTypes/profiles.zcml
Products/ATContentTypes/setuphandlers.py
Products/ATContentTypes/tool.gif
Products/ATContentTypes/utils.py
Products/ATContentTypes/browser/__init__.py
Products/ATContentTypes/browser/calendar.py
Products/ATContentTypes/browser/criteria.py
Products/ATContentTypes/browser/download.py
Products/ATContentTypes/browser/nextprevious.py
Products/ATContentTypes/configuration/__init__.py
Products/ATContentTypes/configuration/component.xml
Products/ATContentTypes/configuration/config.py
Products/ATContentTypes/configuration/datatype.py
Products/ATContentTypes/configuration/schema.py
Products/ATContentTypes/configuration/schema.xml
Products/ATContentTypes/content/__init__.py
Products/ATContentTypes/content/base.py
Products/ATContentTypes/content/document.py
Products/ATContentTypes/content/event.py
Products/ATContentTypes/content/favorite.py
Products/ATContentTypes/content/file.py
Products/ATContentTypes/content/folder.py
Products/ATContentTypes/content/image.py
Products/ATContentTypes/content/link.py
Products/ATContentTypes/content/newsitem.py
Products/ATContentTypes/content/schemata.py
Products/ATContentTypes/content/topic.py
Products/ATContentTypes/criteria/__init__.py
Products/ATContentTypes/criteria/base.py
Products/ATContentTypes/criteria/boolean.py
Products/ATContentTypes/criteria/currentauthor.py
Products/ATContentTypes/criteria/date.py
Products/ATContentTypes/criteria/daterange.py
Products/ATContentTypes/criteria/list.py
Products/ATContentTypes/criteria/path.py
Products/ATContentTypes/criteria/portaltype.py
Products/ATContentTypes/criteria/reference.py
Products/ATContentTypes/criteria/relativepath.py
Products.ATContentTypes-3.0.7.dist-info/METADATA
Products.ATContentTypes-3.0.7.dist-info/WHEEL
Products.ATContentTypes-3.0.7.dist-info/namespace_packages.txt
Products.ATContentTypes-3.0.7.dist-info/top_level.txt
Products.ATContentTypes-3.0.7.dist-info/RECORD
