Metadata-Version: 2.1
Name: Products.ATContentTypes
Version: 3.0.7
Summary: BBB: Default Content Types for Plone 2.1-4.3
Home-page: http://plone.org/
Author: AT Content Types development team
Author-email: plone-developers@lists.sourceforge.net
License: GPL
Keywords: Plone Content Types
Platform: UNKNOWN
Classifier: Development Status :: 6 - Mature
Classifier: Programming Language :: Python
Classifier: Programming Language :: Python :: 2.7
Classifier: Programming Language :: Python :: 2 :: Only
Classifier: Framework :: Plone
Classifier: Framework :: Plone :: 5.2
Classifier: License :: OSI Approved :: GNU General Public License (GPL)
Requires-Python: ==2.7.*
Requires-Dist: setuptools
Requires-Dist: plone.i18n
Requires-Dist: plone.memoize
Requires-Dist: plone.app.blob
Requires-Dist: plone.app.collection
Requires-Dist: plone.app.folder
Requires-Dist: plone.app.imaging
Requires-Dist: plone.app.layout
Requires-Dist: plone.app.widgets (>=1.4.0dev)
Requires-Dist: zope.component
Requires-Dist: zope.i18n
Requires-Dist: zope.i18nmessageid
Requires-Dist: zope.interface
Requires-Dist: zope.publisher
Requires-Dist: zope.tal
Requires-Dist: Products.CMFPlone
Requires-Dist: Products.Archetypes
Requires-Dist: Products.CMFCore
Requires-Dist: Products.CMFDynamicViewFTI
Requires-Dist: Products.CMFFormController
Requires-Dist: Products.GenericSetup
Requires-Dist: Products.MimetypesRegistry
Requires-Dist: Products.PortalTransforms
Requires-Dist: Products.validation
Requires-Dist: Acquisition
Requires-Dist: DateTime
Requires-Dist: ExtensionClass
Requires-Dist: transaction
Requires-Dist: ZConfig
Requires-Dist: ZODB3
Requires-Dist: Zope2
Provides-Extra: test
Requires-Dist: zope.annotation ; extra == 'test'
Requires-Dist: zope.testing ; extra == 'test'
Requires-Dist: plone.app.testing ; extra == 'test'
